nginx_set_conf/__init__.py
nginx_set_conf/config_templates.py
nginx_set_conf/config_verification.py
nginx_set_conf/nginx_set_conf.py
nginx_set_conf/utils.py
nginx_set_conf/templates/__init__.py
nginx_set_conf/templates/all_templates.py
nginx_set_conf/templates/code_server.py
nginx_set_conf/templates/fast_report.py
nginx_set_conf/templates/flowise.py
nginx_set_conf/templates/guacamole.py
nginx_set_conf/templates/kasm.py
nginx_set_conf/templates/mailpit.py
nginx_set_conf/templates/n8n.py
nginx_set_conf/templates/nextcloud.py
nginx_set_conf/templates/odoo_http.py
nginx_set_conf/templates/odoo_ssl.py
nginx_set_conf/templates/pgadmin.py
nginx_set_conf/templates/portainer.py
nginx_set_conf/templates/pwa.py
nginx_set_conf/templates/qdrant.py
nginx_set_conf/templates/redirect.py
nginx_set_conf/templates/redirect_ssl.py
nginx_set_conf/templates/supabase.py
nginx_set_conf-1.8.0.dist-info/licenses/LICENSE.txt
nginx_set_conf-1.8.0.dist-info/METADATA
nginx_set_conf-1.8.0.dist-info/WHEEL
nginx_set_conf-1.8.0.dist-info/entry_points.txt
nginx_set_conf-1.8.0.dist-info/top_level.txt
nginx_set_conf-1.8.0.dist-info/RECORD
