Metadata-Version: 2.4
Name: nginx_set_conf
Version: 1.8.0
Summary: Python library for generating nginx reverse proxy configurations for Docker applications.
Home-page: https://github.com/equitania/nginx-set-conf
Author: Equitania Software GmbH
Author-email: info@equitania.de
Keywords: nginx,configuration,docker,reverse-proxy
Classifier: Development Status :: 5 - Production/Stable
Classifier: Programming Language :: Python :: 3
Classifier: Programming Language :: Python :: 3.10
Classifier: Programming Language :: Python :: 3.11
Classifier: Programming Language :: Python :: 3.12
Classifier: Programming Language :: Python :: 3.13
Classifier: License :: OSI Approved :: GNU Affero General Public License v3
Classifier: Operating System :: OS Independent
Classifier: Environment :: Console
Classifier: Intended Audience :: System Administrators
Classifier: Intended Audience :: Developers
Classifier: Topic :: Internet :: WWW/HTTP :: HTTP Servers
Classifier: Topic :: System :: Systems Administration
Requires-Python: >=3.10
License-File: LICENSE.txt
Requires-Dist: click>=8.2.1
Requires-Dist: PyYAML>=6.0.2
Dynamic: author
Dynamic: author-email
Dynamic: classifier
Dynamic: description
Dynamic: description-content-type
Dynamic: home-page
Dynamic: keywords
Dynamic: license-file
Dynamic: requires-dist
Dynamic: requires-python
Dynamic: summary
